earthscope_sdk/__init__.py
earthscope_sdk/auth/__init__.py
earthscope_sdk/auth/auth_flow.py
earthscope_sdk/auth/client_credentials_flow.py
earthscope_sdk/auth/device_code_flow.py
earthscope_sdk/auth/error.py
earthscope_sdk/client/__init__.py
earthscope_sdk/client/_client.py
earthscope_sdk/client/data_access/__init__.py
earthscope_sdk/client/data_access/_base.py
earthscope_sdk/client/data_access/_service.py
earthscope_sdk/client/data_access/error.py
earthscope_sdk/client/data_access/models.py
earthscope_sdk/client/data_access/_arrow/__init__.py
earthscope_sdk/client/data_access/_arrow/_common.py
earthscope_sdk/client/data_access/_arrow/_gnss.py
earthscope_sdk/client/data_access/_query_plan/__init__.py
earthscope_sdk/client/data_access/_query_plan/_gnss_ephemeris_positions.py
earthscope_sdk/client/data_access/_query_plan/_gnss_observations.py
earthscope_sdk/client/data_access/_query_plan/_query_plan.py
earthscope_sdk/client/data_access/_query_plan/_request_set.py
earthscope_sdk/client/data_access/_query_plan/_util.py
earthscope_sdk/client/discovery/__init__.py
earthscope_sdk/client/discovery/_base.py
earthscope_sdk/client/discovery/_service.py
earthscope_sdk/client/discovery/models.py
earthscope_sdk/client/dropoff/__init__.py
earthscope_sdk/client/dropoff/_base.py
earthscope_sdk/client/dropoff/_multipart_uploader.py
earthscope_sdk/client/dropoff/_service.py
earthscope_sdk/client/dropoff/models.py
earthscope_sdk/client/dropoff/validation.py
earthscope_sdk/client/user/__init__.py
earthscope_sdk/client/user/_base.py
earthscope_sdk/client/user/_service.py
earthscope_sdk/client/user/_util.py
earthscope_sdk/client/user/models.py
earthscope_sdk/common/__init__.py
earthscope_sdk/common/_sync_runner.py
earthscope_sdk/common/client.py
earthscope_sdk/common/context.py
earthscope_sdk/common/service.py
earthscope_sdk/config/__init__.py
earthscope_sdk/config/_bootstrap.py
earthscope_sdk/config/_compat.py
earthscope_sdk/config/_util.py
earthscope_sdk/config/error.py
earthscope_sdk-1.3.0.dist-info/licenses/LICENSE
earthscope_sdk-1.3.0.dist-info/METADATA
earthscope_sdk-1.3.0.dist-info/WHEEL
earthscope_sdk-1.3.0.dist-info/top_level.txt
earthscope_sdk-1.3.0.dist-info/RECORD
