Metadata-Version: 2.4
Name: earthscope-sdk
Version: 1.3.0
Summary: An SDK for EarthScope API
Author-email: EarthScope <data-help@earthscope.org>
License:                                  Apache License
Project-URL: Homepage, https://gitlab.com/earthscope/public/earthscope-sdk
Classifier: License :: OSI Approved :: Apache Software License
Classifier: Programming Language :: Python
Classifier: Programming Language :: Python :: 3
Classifier: Operating System :: OS Independent
Requires-Python: >=3.9
License-File: LICENSE
Requires-Dist: httpx>=0.27.0
Requires-Dist: pydantic-settings[toml]>=2.8.0
Requires-Dist: stamina>=24.3.0
Requires-Dist: aioboto3
Requires-Dist: aiofiles
Requires-Dist: pymseed<1.0.0,>=0.2.0
Provides-Extra: arrow
Requires-Dist: pyarrow>=20.0.0; extra == "arrow"
Requires-Dist: pyarrow-stubs>=20.0.0; extra == "arrow"
Provides-Extra: dev
Requires-Dist: bumpver; extra == "dev"
Requires-Dist: build; extra == "dev"
Requires-Dist: pytest; extra == "dev"
Requires-Dist: twine; extra == "dev"
Requires-Dist: pip-tools; extra == "dev"
Requires-Dist: pre-commit; extra == "dev"
Requires-Dist: pytest-httpx; extra == "dev"
Requires-Dist: pytest-asyncio; extra == "dev"
Requires-Dist: ruff; extra == "dev"
Dynamic: license-file
